fastucp/__init__.py
fastucp/builders.py
fastucp/client.py
fastucp/core.py
fastucp/exceptions.py
fastucp/presets.py
fastucp/security.py
fastucp/store.py
fastucp/types.py
fastucp/utils.py
fastucp/models/__init__.py
fastucp/models/_internal.py
fastucp/models/discovery/__init__.py
fastucp/models/discovery/profile_schema.py
fastucp/models/handlers/__init__.py
fastucp/models/handlers/tokenization/__init__.py
fastucp/models/handlers/tokenization/openapi.py
fastucp/models/schemas/__init__.py
fastucp/models/schemas/capability.py
fastucp/models/schemas/ucp.py
fastucp/models/schemas/shopping/__init__.py
fastucp/models/schemas/shopping/ap2_mandate.py
fastucp/models/schemas/shopping/buyer_consent_create_req.py
fastucp/models/schemas/shopping/buyer_consent_resp.py
fastucp/models/schemas/shopping/buyer_consent_update_req.py
fastucp/models/schemas/shopping/checkout_create_req.py
fastucp/models/schemas/shopping/checkout_resp.py
fastucp/models/schemas/shopping/checkout_update_req.py
fastucp/models/schemas/shopping/discount_create_req.py
fastucp/models/schemas/shopping/discount_resp.py
fastucp/models/schemas/shopping/discount_update_req.py
fastucp/models/schemas/shopping/fulfillment_create_req.py
fastucp/models/schemas/shopping/fulfillment_resp.py
fastucp/models/schemas/shopping/fulfillment_update_req.py
fastucp/models/schemas/shopping/order.py
fastucp/models/schemas/shopping/payment_create_req.py
fastucp/models/schemas/shopping/payment_data.py
fastucp/models/schemas/shopping/payment_resp.py
fastucp/models/schemas/shopping/payment_update_req.py
fastucp/models/schemas/shopping/types/__init__.py
fastucp/models/schemas/shopping/types/account_info.py
fastucp/models/schemas/shopping/types/adjustment.py
fastucp/models/schemas/shopping/types/binding.py
fastucp/models/schemas/shopping/types/buyer.py
fastucp/models/schemas/shopping/types/card_credential.py
fastucp/models/schemas/shopping/types/card_payment_instrument.py
fastucp/models/schemas/shopping/types/expectation.py
fastucp_python-0.1.2.dist-info/licenses/LICENSE
fastucp_python-0.1.2.dist-info/METADATA
fastucp_python-0.1.2.dist-info/WHEEL
fastucp_python-0.1.2.dist-info/top_level.txt
fastucp_python-0.1.2.dist-info/RECORD
