Metadata-Version: 2.4
Name: fastucp-python
Version: 0.1.2
Summary: FastAPI based implementation of Universal Commerce Protocol
Author-email: Mehmet Hilmi Emel <mehmethilmi81@gmail.com>
Project-URL: Homepage, https://github.com/MehmetHilmiEmel/fastucp
Project-URL: Bug Tracker, https://github.com/MehmetHilmiEmel/fastucp/issues
Classifier: Programming Language :: Python :: 3
Classifier: License :: OSI Approved :: MIT License
Classifier: Operating System :: OS Independent
Classifier: Framework :: FastAPI
Requires-Python: >=3.10
License-File: LICENSE
Requires-Dist: fastapi>=0.100.0
Requires-Dist: uvicorn>=0.20.0
Requires-Dist: pydantic>=2.5.0
Requires-Dist: requests>=2.30.0
Requires-Dist: jwcrypto==1.5.6
Dynamic: license-file
